wrappy/__init__.py
wrappy-0.2.7.dist-info/LICENSE
wrappy-0.2.7.dist-info/METADATA
wrappy-0.2.7.dist-info/WHEEL
wrappy-0.2.7.dist-info/top_level.txt
wrappy-0.2.7.dist-info/RECORD
