Metadata-Version: 2.1
Name: wrappy
Version: 0.2.7
Summary: Decorators for common developer utility.
Home-page: https://github.com/haochuanwei/wrappy
Author: Haochuan Wei
Author-email: haochuanwei@yahoo.com
Classifier: Programming Language :: Python :: 3
Classifier: Development Status :: 4 - Beta
Classifier: License :: OSI Approved :: MIT License
Classifier: Operating System :: OS Independent
Requires-Python: >=3.6
License-File: LICENSE
Requires-Dist: wasabi (>=0.4)
Requires-Dist: dill (>=0.3.1.1)
